EM_data_analysis/__init__.py
EM_data_analysis/morph_analysis.py
EM_data_analysis-1.1.1.dist-info/LICENSE.txt
EM_data_analysis-1.1.1.dist-info/METADATA
EM_data_analysis-1.1.1.dist-info/WHEEL
EM_data_analysis-1.1.1.dist-info/top_level.txt
EM_data_analysis-1.1.1.dist-info/RECORD
