Metadata-Version: 2.1
Name: EM-data-analysis
Version: 1.1.1
Summary: A Python package for EM data analysis
Home-page: https://github.com/Nomeutente1/EM_data_analysis
Author: Mattia Lizzano, Giorgio Divitini
Author-email: mattializzano@gmail.com
Classifier: Programming Language :: Python :: 3
Classifier: License :: OSI Approved :: MIT License
Classifier: Operating System :: OS Independent
Requires-Python: >=3.6
License-File: LICENSE.txt
Requires-Dist: opencv-python
Requires-Dist: numpy
Requires-Dist: porespy
Requires-Dist: matplotlib
Requires-Dist: openpnm
Requires-Dist: scipy
Requires-Dist: pandas
Requires-Dist: moviepy
Requires-Dist: IPython
Requires-Dist: scikit-image
Requires-Dist: dataframe-image
